konectipy/__init__.py
konectipy/konectipy.py
konectipy-0.0.5.dist-info/LICENSE
konectipy-0.0.5.dist-info/METADATA
konectipy-0.0.5.dist-info/WHEEL
konectipy-0.0.5.dist-info/top_level.txt
konectipy-0.0.5.dist-info/RECORD
