Metadata-Version: 2.1
Name: konectipy
Version: 0.0.5
Summary: A network analyzer
Home-page: https://github.com/AkiMosi/konectipy
Author: Akileshvar A
Author-email: akileshvar008@gmail.com
License: UNKNOWN
Platform: UNKNOWN
Classifier: Programming Language :: Python :: 3
Classifier: License :: OSI Approved :: MIT License
Classifier: Operating System :: OS Independent
Requires-Python: >=3.6
